rastermodel/__init__.py
rastermodel/rastermodeling.py
rastermodel-0.0.4.dist-info/LICENSE
rastermodel-0.0.4.dist-info/METADATA
rastermodel-0.0.4.dist-info/WHEEL
rastermodel-0.0.4.dist-info/top_level.txt
rastermodel-0.0.4.dist-info/RECORD
