Metadata-Version: 2.1
Name: rastermodel
Version: 0.0.4
Summary: Modeling with rasters and images
Home-page: https://github.com/pypa/sampleproject
Author: Benoit Parmentier
Author-email: benoit.parmentier@gmail.com
License: UNKNOWN
Platform: UNKNOWN
Classifier: Programming Language :: Python :: 3
Classifier: License :: OSI Approved :: MIT License
Classifier: Operating System :: OS Independent
